cuda_checker/__init__.py
cuda_checker/check.py
cuda_checker/cli.py
cuda_checker-0.2.0.dist-info/entry_points.txt
cuda_checker-0.2.0.dist-info/LICENSE
cuda_checker-0.2.0.dist-info/WHEEL
cuda_checker-0.2.0.dist-info/METADATA
cuda_checker-0.2.0.dist-info/RECORD
