Metadata-Version: 2.1
Name: cuda-checker
Version: 0.2.0
Summary: NVIDIA CUDA checker for pythonn deeplearning project.
Home-page: https://github.com/kagemeka/cuda-checker#readme
License: MIT
Keywords: cuda,python,deeplearning,tensorflow,pytorch
Author: Hiroshi Tsuyuki
Author-email: kagemeka1@gmail.com
Maintainer: Hiroshi Tsuyuki
Maintainer-email: kagemeka1@gmail.com
Requires-Python: >=3.9,<3.10
Classifier: License :: OSI Approved :: MIT License
Classifier: Operating System :: OS Independent
Classifier: Programming Language :: Python :: 3
Classifier: Programming Language :: Python :: 3.9
Provides-Extra: docs
Requires-Dist: furo; extra == "docs"
Requires-Dist: myst-parser; extra == "docs"
Requires-Dist: pdoc3; extra == "docs"
Requires-Dist: pydata-sphinx-theme; extra == "docs"
Requires-Dist: python-docs-theme; extra == "docs"
Requires-Dist: sphinx-book-theme; extra == "docs"
Requires-Dist: sphinx-theme-pd; extra == "docs"
Requires-Dist: sphinx; extra == "docs"
Requires-Dist: sphinx_rtd_theme (<=2.0.0); extra == "docs"
Requires-Dist: sphinxcontrib-mermaid; extra == "docs"
Requires-Dist: tensorflow
Requires-Dist: torch
Project-URL: Documentation, https://cuda-checker.readthedocs.io
Project-URL: Repository, https://github.com/kagemeka/cuda-checker
